ConcurrentDatabase/ColumnWrapper.py
ConcurrentDatabase/Database.py
ConcurrentDatabase/DynamicEntry.py
ConcurrentDatabase/DynamicTable.py
ConcurrentDatabase/__init__.py
ConcurrentDatabase-0.0.11.dist-info/METADATA
ConcurrentDatabase-0.0.11.dist-info/WHEEL
ConcurrentDatabase-0.0.11.dist-info/top_level.txt
ConcurrentDatabase-0.0.11.dist-info/RECORD
