Metadata-Version: 2.1
Name: ConcurrentDatabase
Version: 0.0.11
Summary: A SQLite wrapper that allows for object oriented database access.
Home-page: 
Author: Jay S
Author-email: 
Classifier: Programming Language :: Python :: 3
Classifier: License :: OSI Approved :: MIT License
Requires-Python: >=3.8
